patchpyro/__init__.py
patchpyro/listen/__init__.py
patchpyro/listen/listen.py
patchpyro/utils/__init__.py
patchpyro/utils/utils.py
patchpyro-2.0.3.dist-info/COPYING
patchpyro-2.0.3.dist-info/COPYING.lesser
patchpyro-2.0.3.dist-info/METADATA
patchpyro-2.0.3.dist-info/NOTICE
patchpyro-2.0.3.dist-info/WHEEL
patchpyro-2.0.3.dist-info/top_level.txt
patchpyro-2.0.3.dist-info/RECORD
