Metadata-Version: 2.1
Name: patchpyro
Version: 2.0.3
Summary: A modified pyromod by www.da.gd/aditya
Home-page: https://github.com/adityaprasad502/patchpyro
Author: Cezar H. & adityaprasad502
License: LGPLv3+
Classifier: Programming Language :: Python :: 3
Classifier: License :: OSI Approved :: GNU Lesser General Public License v3 or later (LGPLv3+)
Classifier: Operating System :: OS Independent
Requires-Python: >=3.9
License-File: COPYING
License-File: COPYING.lesser
License-File: NOTICE
Requires-Dist: pyrogram (>=2.0.69)
